examples/__init__.py
examples/basic_chat.py
tests/__init__.py
tests/conftest.py
tests/mock_data.py
tests/test_client.py
voxta_client/__init__.py
voxta_client/audio_client.py
voxta_client/client.py
voxta_client/constants.py
voxta_client/exceptions.py
voxta_client/models.py
voxta_client/transport.py
voxta_client-0.2.0.dist-info/licenses/LICENSE
voxta_client-0.2.0.dist-info/METADATA
voxta_client-0.2.0.dist-info/WHEEL
voxta_client-0.2.0.dist-info/top_level.txt
voxta_client-0.2.0.dist-info/RECORD
